wya/__init__.py
wya/app.py
wya/dnsops.py
wya/ipquery.py
wya/log.py
wya-0.2.1.dist-info/entry_points.txt
wya-0.2.1.dist-info/licenses/LICENSE
wya-0.2.1.dist-info/WHEEL
wya-0.2.1.dist-info/METADATA
wya-0.2.1.dist-info/RECORD
