Metadata-Version: 2.4
Name: wya
Version: 0.2.1
Summary: wya
Author-email: gottaeat <mss@tutanota.de>
Classifier: License :: OSI Approved :: GNU General Public License v3 or later (GPLv3+)
License-File: LICENSE
Requires-Dist: dnspython >= 2.6.1
Requires-Dist: flask >= 3.0.3
Requires-Dist: flask_limiter >= 3.8.0
Requires-Dist: maxminddb >= 2.6.2
Requires-Dist: paste >= 3.10.1
Requires-Dist: waitress >= 3.0.0
Project-URL: Source, http://github.com/gottaeat/wya
